run.py
setup.py
zquery/__init__.py
zquery/answer.py
zquery/client.py
zquery/collection.py
zquery/column.py
zquery/error.py
zquery/login.py
zquery/post.py
zquery/queryPprint.py
zquery/question.py
zquery/user.py
zquery/utils.py
zquery/zquery.py
zquery.egg-info/PKG-INFO
zquery.egg-info/SOURCES.txt
zquery.egg-info/dependency_links.txt
zquery.egg-info/entry_points.txt
zquery.egg-info/not-zip-safe
zquery.egg-info/requires.txt
zquery.egg-info/top_level.txt