Metadata-Version: 1.1
Name: zquery
Version: 2.0.0
Summary: Zhihu UNOFFICIAL API library based on Python3
Home-page: https://github.com/WiseDoge/zquery
Author: wisedoge
Author-email: wisedoge@outlook.com
License: apache 2.0
Platform: any
Classifier: Environment :: Console
Classifier: Programming Language :: Python
Classifier: Programming Language :: Python :: 3
Classifier: Programming Language :: Python :: 3.1
Classifier: Programming Language :: Python :: 3.2
Classifier: Programming Language :: Python :: 3.3
Classifier: Programming Language :: Python :: 3.4
Classifier: Programming Language :: Python :: 3.5
Classifier: Programming Language :: Python :: Implementation :: CPython
